stella_logger/__init__.py
stella_logger/_internal/__init__.py
stella_logger/_internal/compat.py
stella_logger/_internal/errors.py
stella_logger/core/__init__.py
stella_logger/core/adapter.py
stella_logger/core/reserved.py
stella_logger/core/settings.py
stella_logger/core/severity.py
stella_logger/error/__init__.py
stella_logger/error/app_error.py
stella_logger/logger/__init__.py
stella_logger/logger/stella_logger.py
stella_logger/py.typed
stella_logger/schema/__init__.py
stella_logger/schema/definition.py
stella_logger/schema/formatter.py
stella_logger/schema/registry.py
stella_logger/schema/types.py
stella_logger-1.0.2.dist-info/METADATA
stella_logger-1.0.2.dist-info/WHEEL
stella_logger-1.0.2.dist-info/licenses/LICENSE
stella_logger-1.0.2.dist-info/RECORD
