Metadata-Version: 2.4
Name: stella-logger
Version: 1.0.2
Summary: Strict and safe logging SDK.
License: MIT
License-File: LICENSE
Keywords: logging
Author: ricky-rehivo
Author-email: ricky.rehivo@gmail.com
Requires-Python: >=3.10
Classifier: Development Status :: 3 - Alpha
Classifier: Intended Audience :: Developers
Classifier: License :: OSI Approved :: MIT License
Classifier: Programming Language :: Python :: 3
Classifier: Programming Language :: Python :: 3.10
Classifier: Programming Language :: Python :: 3.11
Classifier: Programming Language :: Python :: 3.12
Classifier: Programming Language :: Python :: 3.13
Classifier: Programming Language :: Python :: 3.14
Classifier: Programming Language :: Python :: 3 :: Only
Classifier: Topic :: System :: Logging
Classifier: Typing :: Typed
Requires-Dist: pydantic (>=2.6.0)
Requires-Dist: typing-extensions (>=4.9.0)
Project-URL: Changelog, https://github.com/stellavoid-org/stella-logger/releases
Project-URL: Homepage, https://github.com/stellavoid-org/stella-logger
Project-URL: Issues, https://github.com/stellavoid-org/stella-logger/issues
Project-URL: Repository, https://github.com/stellavoid-org/stella-loggger
